textcraft.py
textcraft_py-0.1.3.dist-info/licenses/LICENSE
textcraft_py-0.1.3.dist-info/METADATA
textcraft_py-0.1.3.dist-info/WHEEL
textcraft_py-0.1.3.dist-info/top_level.txt
textcraft_py-0.1.3.dist-info/RECORD
