Metadata-Version: 2.4
Name: textcraft-py
Version: 0.1.3
Summary: A lightweight, beginner-friendly Python module for text transformation and analysis
Author: O-sama12
License: MIT
Classifier: Programming Language :: Python :: 3
Classifier: License :: OSI Approved :: MIT License
Classifier: Operating System :: OS Independent
Requires-Python: >=3.8
License-File: LICENSE
Dynamic: license-file
